[
    {
        "itemName": "Wed Band",
        "longICN": "031143005649100100",
        "details": [
            "W/G",
            "14 KT.",
            "APPRX 10.1 GRM",
            "MODERN STYLE",
            "RS 8",
            "1",
            "RND SHP",
            "DIA-TEST POS STN",
            "@ 13 PTS EA.",
            "2",
            "RND SHP",
            "DIA-TEST POS STN",
            "@ 10 PTS EA."
        ],
        "price": 549.99,
        "distance": 318.9739,
        "storeNumber": "03114",
        "shortName": "C3114"
    },
    {
        "itemName": "Wed Band",
        "longICN": "031144003104200100",
        "details": [
            "Y/G",
            "10 KT.",
            "APPRX 2.3 GRM",
            "MODERN STYLE",
            "RS 10.5",
            "10",
            "RND SHP",
            "DIA-TEST POS STN",
            "@ 3 PTS EA."
        ],
        "price": 119.99,
        "distance": 318.9739,
        "storeNumber": "03114",
        "shortName": "C3114"
    },
    {
        "itemName": "Wed Band",
        "longICN": "031144003442200100",
        "details": [
            "Y/G",
            "10 KT.",
            "APPRX .8 GRM",
            "RS 7"
        ],
        "price": 29.99,
        "distance": 318.9739,
        "storeNumber": "03114",
        "shortName": "C3114"
    },
    {
        "itemName": "Wed Band",
        "longICN": "031144003547200100",
        "details": [
            "Y/G",
            "14 KT.",
            "APPRX 2.7 GRM",
            "RS 10.5"
        ],
        "price": 99.99,
        "distance": 318.9739,
        "storeNumber": "03114",
        "shortName": "C3114"
    },
    {
        "itemName": "Wed Band",
        "longICN": "031144003580200100",
        "details": [
            "W/G",
            "10 KT.",
            "APPRX 3.8 GRM",
            "MODERN STYLE",
            "GENDER MAN'S",
            "RS 10.5",
            "10",
            "RND SHP",
            "DIA-TEST POS STN",
            "@ 1 PTS EA."
        ],
        "price": 139.99,
        "distance": 318.9739,
        "storeNumber": "03114",
        "shortName": "C3114"
    },
    {
        "itemName": "Wed Band",
        "longICN": "031144003702200100",
        "details": [
            "Y/G",
            "14 KT.",
            "APPRX 4.6 GRM",
            "GENDER MAN'S",
            "RS 12"
        ],
        "price": 179.99,
        "distance": 318.9739,
        "storeNumber": "03114",
        "shortName": "C3114"
    },
    {
        "itemName": "Wed Band",
        "longICN": "031144003708200100",
        "details": [
            "W/G",
            "14 KT.",
            "APPRX 6.2 GRM",
            "RS 7.5",
            "4",
            "FANCY SHP",
            "DIA-TEST POS STN",
            "@ 45 PTS EA.",
            "8",
            "FANCY SHP",
            "DIA-TEST POS STN",
            "@ 8 PTS EA."
        ],
        "price": 1799.99,
        "distance": 318.9739,
        "storeNumber": "03114",
        "shortName": "C3114"
    },
    {
        "itemName": "Wed Band",
        "longICN": "031144003721200100",
        "details": [
            "Y/G",
            "10 KT.",
            "APPRX 4.7 GRM",
            "GENDER MENS",
            "RS 10",
            "3",
            "RND SHP",
            "DIA-TEST POS STN",
            "@ 4 PTS EA."
        ],
        "price": 169.99,
        "distance": 318.9739,
        "storeNumber": "03114",
        "shortName": "C3114"
    },
    {
        "itemName": "Wed Band",
        "longICN": "031144003841200100",
        "details": [
            "Y/G",
            "14 KT.",
            "APPRX 2.4 GRM",
            "MODERN STYLE",
            "GENDER WOMANS",
            "RS 8.5",
            "1",
            "RND SHP",
            "DIA-TEST POS STN",
            "@ 33 PTS EA."
        ],
        "price": 349.99,
        "distance": 318.9739,
        "storeNumber": "03114",
        "shortName": "C3114"
    },
    {
        "itemName": "Wed Band",
        "longICN": "031144005869100100",
        "details": [
            "Y/G",
            "10 KT.",
            "APPRX 1.2 GRM",
            "MODERN STYLE",
            "GENDER WOMANS",
            "RS 7.5",
            "12",
            "RND SHP",
            "DIA-TEST POS STN",
            "@ 1 PTS EA."
        ],
        "price": 49.99,
        "distance": 318.9739,
        "storeNumber": "03114",
        "shortName": "C3114"
    },
    {
        "itemName": "Wed Band",
        "longICN": "031144005899100100",
        "details": [
            "Y/G",
            "10 KT.",
            "APPRX 2.3 GRM",
            "GENDER WOMANS",
            "RS 7.75",
            "1",
            "round SHP",
            "DIA-TEST POS STN",
            "@ 10 PTS EA.",
            "2",
            "round SHP",
            "DIA-TEST POS STN",
            "@ 5 PTS EA."
        ],
        "price": 129.99,
        "distance": 318.9739,
        "storeNumber": "03114",
        "shortName": "C3114"
    },
    {
        "itemName": "Wed Band",
        "longICN": "031144005982100200",
        "details": [
            "W/G",
            "10 KT.",
            "APPRX 3.8 GRM",
            "TRADITIONAL STYLE",
            "GENDER WOMANS",
            "RS 6",
            "12",
            "square SHP",
            "DIA-TEST POS STN",
            "@ 8 PTS EA.",
            "8",
            "round SHP",
            "DIA-TEST POS STN",
            "@ 3 PTS EA."
        ],
        "price": 349.99,
        "distance": 318.9739,
        "storeNumber": "03114",
        "shortName": "C3114"
    },
    {
        "itemName": "Wed Band",
        "longICN": "031144006013100100",
        "details": [
            "W/G",
            "14 KT.",
            "APPRX 5.9 GRM",
            "MODERN STYLE",
            "GENDER WOMENS",
            "RS 7.75",
            "1",
            "RND SHP",
            "DIA-TEST POS STN",
            "@ 21 PTS EA.",
            "26",
            "RND SHP",
            "DIA-TEST POS STN",
            "@ 17 PTS EA."
        ],
        "price": 2099.99,
        "distance": 318.9739,
        "storeNumber": "03114",
        "shortName": "C3114"
    },
    {
        "itemName": "Wed Band",
        "longICN": "031144006226100100",
        "details": [
            "Y/G",
            "10 KT.",
            "APPRX 2.8 GRM",
            "TRADITIONAL STYLE",
            "GENDER WOMANS",
            "RS 7.5",
            "36",
            "RND SHP",
            "DIA-TEST POS STN",
            "@ 2.5 PTS EA."
        ],
        "price": 199.99,
        "distance": 318.9739,
        "storeNumber": "03114",
        "shortName": "C3114"
    },
    {
        "itemName": "Wed Band",
        "longICN": "031144006326100200",
        "details": [
            "Y/G AND W/G",
            "14 KT.",
            "APPRX 6.5 GRM",
            "GENDER MAN'S",
            "RS 11"
        ],
        "price": 249.99,
        "distance": 318.9739,
        "storeNumber": "03114",
        "shortName": "C3114"
    },
    {
        "itemName": "Wed Band",
        "longICN": "031144006747100100",
        "details": [
            "W/G",
            "14 KT.",
            "APPRX 14.9 GRM",
            "RS 7.5",
            "4",
            "FANCY SHP",
            "DIA-TEST POS STN",
            "@ 33 PTS EA.",
            "26",
            "RND SHP",
            "DIA-TEST POS STN",
            "@ 3 PTS EA.",
            "8",
            "RND SHP",
            "DIA-TEST POS STN",
            "@ 9 PTS EA."
        ],
        "price": 2499.99,
        "distance": 318.9739,
        "storeNumber": "03114",
        "shortName": "C3114"
    },
    {
        "itemName": "Wed Band",
        "longICN": "031144007001100100",
        "details": [
            "Y/G",
            "14 KT.",
            "APPRX 3.0 GRM",
            "RS 7",
            "10",
            "RND SHP",
            "DIA-TEST POS STN",
            "@ 3 PTS EA."
        ],
        "price": 139.99,
        "distance": 318.9739,
        "storeNumber": "03114",
        "shortName": "C3114"
    },
    {
        "itemName": "Wed Band",
        "longICN": "031144007235100100",
        "details": [
            "W/G",
            "14 KT.",
            "APPRX 8.6 GRM",
            "RS 7",
            "12",
            "FANCY SHP",
            "DIA-TEST POS STN",
            "@ 15 PTS EA.",
            "24",
            "RND SHP",
            "DIA-TEST POS STN",
            "@ 2.5 PTS EA.",
            "8",
            "BAG SHP",
            "DIA-TEST POS STN",
            "@ 4 PTS EA."
        ],
        "price": 2299.99,
        "distance": 318.9739,
        "storeNumber": "03114",
        "shortName": "C3114"
    },
    {
        "itemName": "Misc Wed Band",
        "longICN": "031144007346100100",
        "details": [
            "W/G",
            "14 KT.",
            "APPRX 1.9 GRM",
            "WAVE LOOK STYLE",
            "GENDER WOMENS",
            "RS 7.25",
            "36",
            "RND SHP",
            "DIA-TEST POS STN",
            "@ 1.5 PTS EA."
        ],
        "price": 199.99,
        "distance": 318.9739,
        "storeNumber": "03114",
        "shortName": "C3114"
    },
    {
        "itemName": "Wed Band",
        "longICN": "031144007418100100",
        "details": [
            "W/G",
            "14 KT.",
            "APPRX 4 GRM",
            "RS 7.25",
            "1",
            "RND SHP",
            "DIA-TEST POS STN",
            "@ 35 PTS EA.",
            "36",
            "RND SHP",
            "DIA-TEST POS STN",
            "@ 0.75 PTS EA.",
            "12",
            "RND SHP",
            "DIA-TEST POS STN",
            "@ 2.5 PTS EA."
        ],
        "price": 499.99,
        "distance": 318.9739,
        "storeNumber": "03114",
        "shortName": "C3114"
    },
    {
        "itemName": "Wed Band",
        "longICN": "031144007550100200",
        "details": [
            "Y/G",
            "14 KT.",
            "APPRX 2.6 GRM",
            "GENDER MAN'S",
            "RS 9"
        ],
        "price": 69.99,
        "distance": 318.9739,
        "storeNumber": "03114",
        "shortName": "C3114"
    },
    {
        "itemName": "Wed Band",
        "longICN": "031144007847100100",
        "details": [
            "W/G",
            "14 KT.",
            "APPRX 4.3 GRM",
            "GENDER WOMANS",
            "RS 8.5",
            "10",
            "squ SHP",
            "DIA-TEST POS STN",
            "@ 8 PTS EA."
        ],
        "price": 299.99,
        "distance": 318.9739,
        "storeNumber": "03114",
        "shortName": "C3114"
    },
    {
        "itemName": "Wed Band",
        "longICN": "030673008725100100",
        "details": [
            "Y/G",
            "14 KT.",
            "APPRX 3.7 GRM",
            "TRADITIONAL STYLE",
            "GENDER MAN'S",
            "RS 9.5"
        ],
        "price": 159.99,
        "distance": 323.8009,
        "storeNumber": "03067",
        "shortName": "C3067"
    },
    {
        "itemName": "Wed Band",
        "longICN": "030673008897100200",
        "details": [
            "Y/G",
            "14 KT.",
            "APPRX 6.9 GRM",
            "TRADITIONAL STYLE",
            "GENDER MAN'S",
            "RS 10.5",
            "7",
            "RND SHP",
            "DIA-TEST POS STN",
            "@ 6 PTS EA."
        ],
        "price": 479.99,
        "distance": 323.8009,
        "storeNumber": "03067",
        "shortName": "C3067"
    },
    {
        "itemName": "Wed Band",
        "longICN": "030674004698200100",
        "details": [
            "W/G",
            "10 KT.",
            "APPRX 1.5 GRM",
            "TRADITIONAL STYLE",
            "GENDER WOMANS",
            "RS 6.5",
            "20",
            "RND SHP",
            "DIA-TEST POS STN",
            "@ 0.50 PTS EA."
        ],
        "price": 49.99,
        "distance": 323.8009,
        "storeNumber": "03067",
        "shortName": "C3067"
    },
    {
        "itemName": "Wed Band",
        "longICN": "030674004701200100",
        "details": [
            "Y/G",
            "14 KT.",
            "APPRX 7.1 GRM",
            "MODERN STYLE",
            "GENDER MAN'S",
            "RS 11",
            "8",
            "RND SHP",
            "DIA-TEST POS STN",
            "@ 3 PTS EA."
        ],
        "price": 329.99,
        "distance": 323.8009,
        "storeNumber": "03067",
        "shortName": "C3067"
    },
    {
        "itemName": "Wed Band",
        "longICN": "030674004795200100",
        "details": [
            "W/G",
            "14 KT.",
            "APPRX 3.6 GRM",
            "TRADITIONAL STYLE",
            "RS 9.5"
        ],
        "price": 139.99,
        "distance": 323.8009,
        "storeNumber": "03067",
        "shortName": "C3067"
    },
    {
        "itemName": "Wed Band",
        "longICN": "030674004934200100",
        "details": [
            "Y/G AND W/G",
            "14 KT.",
            "APPRX 4.4 GRM",
            "RS 11"
        ],
        "price": 179.99,
        "distance": 323.8009,
        "storeNumber": "03067",
        "shortName": "C3067"
    },
    {
        "itemName": "Wed Band",
        "longICN": "030674004997200100",
        "details": [
            "W/G",
            "10 KT.",
            "APPRX 3.5 GRM",
            "RS 10"
        ],
        "price": 119.99,
        "distance": 323.8009,
        "storeNumber": "03067",
        "shortName": "C3067"
    },
    {
        "itemName": "Wed Band",
        "longICN": "030674005007200100",
        "details": [
            "W/G",
            "14 KT.",
            "APPRX 1.9 GRM",
            "TRADITIONAL STYLE",
            "GENDER WOMANS",
            "RS 5.5",
            "21",
            "RND SHP",
            "DIA-TEST POS STN",
            "@ 1 PTS EA."
        ],
        "price": 139.99,
        "distance": 323.8009,
        "storeNumber": "03067",
        "shortName": "C3067"
    },
    {
        "itemName": "Wed Band",
        "longICN": "030674005108200100",
        "details": [
            "W/G",
            "10 KT.",
            "APPRX 4.1 GRM",
            "TRADITIONAL STYLE",
            "GENDER MAN'S",
            "RS 12.5"
        ],
        "price": 119.99,
        "distance": 323.8009,
        "storeNumber": "03067",
        "shortName": "C3067"
    },
    {
        "itemName": "Wed Band",
        "longICN": "030674005200200100",
        "details": [
            "Y/G",
            "10 KT.",
            "APPRX 1.9 GRM",
            "TRADITIONAL STYLE",
            "GENDER WOMANS",
            "RS 7",
            "1",
            "RND SHP",
            "DIA-TEST POS STN",
            "@ 0.50 PTS EA."
        ],
        "price": 59.95,
        "distance": 323.8009,
        "storeNumber": "03067",
        "shortName": "C3067"
    },
    {
        "itemName": "Wed Band",
        "longICN": "030674005351200100",
        "details": [
            "Y/G",
            "10 KT.",
            "APPRX 2.7 GRM",
            "RS 10"
        ],
        "price": 99.99,
        "distance": 323.8009,
        "storeNumber": "03067",
        "shortName": "C3067"
    },
    {
        "itemName": "Wed Band",
        "longICN": "030674009720100100",
        "details": [
            "W/G",
            "14 KT.",
            "APPRX 9.2 GRM",
            "MODERN STYLE",
            "GENDER MAN'S",
            "RS 11"
        ],
        "price": 359.99,
        "distance": 323.8009,
        "storeNumber": "03067",
        "shortName": "C3067"
    },
    {
        "itemName": "Wed Band",
        "longICN": "030674009844100100",
        "details": [
            "W/G",
            "10 KT.",
            "APPRX 5 GRM",
            "TRADITIONAL STYLE",
            "GENDER MAN'S",
            "RS 9.25"
        ],
        "price": 159.99,
        "distance": 323.8009,
        "storeNumber": "03067",
        "shortName": "C3067"
    },
    {
        "itemName": "Wed Band",
        "longICN": "030674010175100200",
        "details": [
            "Y/G",
            "10 KT.",
            "APPRX 2.4 GRM",
            "RS 7",
            "7",
            "RND SHP",
            "DIA-TEST POS STN",
            "@ 1 PTS EA.",
            "6",
            "BAG SHP",
            "DIA-TEST POS STN",
            "@ 1 PTS EA."
        ],
        "price": 99.99,
        "distance": 323.8009,
        "storeNumber": "03067",
        "shortName": "C3067"
    },
    {
        "itemName": "Wed Band",
        "longICN": "030674010478100100",
        "details": [
            "Y/G",
            "10 KT.",
            "APPRX 1.9 GRM",
            "MODERN STYLE",
            "GENDER WOMANS",
            "RS 8.5",
            "12",
            "RND SHP",
            "DIA-TEST POS STN",
            "@ 1 PTS EA."
        ],
        "price": 69.99,
        "distance": 323.8009,
        "storeNumber": "03067",
        "shortName": "C3067"
    },
    {
        "itemName": "Wed Band",
        "longICN": "030674010733100100",
        "details": [
            "Y/G",
            "14 KT.",
            "APPRX 4.4 GRM",
            "MODERN STYLE",
            "RS 6.5",
            "10",
            "SQUARE SHP",
            "DIA-TEST POS STN",
            "@ 8 PTS EA."
        ],
        "price": 449.99,
        "distance": 323.8009,
        "storeNumber": "03067",
        "shortName": "C3067"
    },
    {
        "itemName": "Wed Band",
        "longICN": "030674010901100100",
        "details": [
            "Y/G",
            "14 KT.",
            "APPRX 6.6 GRM",
            "TRADITIONAL STYLE",
            "GENDER MAN'S",
            "RS 9.5",
            "9",
            "SQUARE SHP",
            "DIA-TEST POS STN",
            "@ 8 PTS EA."
        ],
        "price": 524.99,
        "distance": 323.8009,
        "storeNumber": "03067",
        "shortName": "C3067"
    },
    {
        "itemName": "Wed Band",
        "longICN": "030674010908100100",
        "details": [
            "W/G",
            "14 KT.",
            "APPRX 2.2 GRM",
            "MODERN STYLE",
            "GENDER WOMANS",
            "RS 7",
            "17",
            "RND SHP",
            "DIA-TEST POS STN",
            "@ 1 PTS EA."
        ],
        "price": 129.99,
        "distance": 323.8009,
        "storeNumber": "03067",
        "shortName": "C3067"
    },
    {
        "itemName": "Wed Band",
        "longICN": "030674011781100100",
        "details": [
            "Y/G",
            "14 KT.",
            "APPRX 4.6 GRM",
            "RS 9"
        ],
        "price": 169.99,
        "distance": 323.8009,
        "storeNumber": "03067",
        "shortName": "C3067"
    },
    {
        "itemName": "Wed Band",
        "longICN": "030674011823100100",
        "details": [
            "Y/G",
            "10 KT.",
            "APPRX 3.5 GRM",
            "TRADITIONAL STYLE",
            "GENDER MAN'S",
            "RS 11"
        ],
        "price": 119.99,
        "distance": 323.8009,
        "storeNumber": "03067",
        "shortName": "C3067"
    },
    {
        "itemName": "Wed Band",
        "longICN": "030674012513100100",
        "details": [
            "W/G",
            "14 KT.",
            "APPRX 1.7 GRM",
            "RS 7.5",
            "11",
            "RND SHP",
            "DIA-TEST POS STN",
            "@ 2 PTS EA."
        ],
        "price": 129.99,
        "distance": 323.8009,
        "storeNumber": "03067",
        "shortName": "C3067"
    },
    {
        "itemName": "Wed Band",
        "longICN": "030674012710100100",
        "details": [
            "Y/G",
            "14 KT.",
            "APPRX 2.7 GRM",
            "TRADITIONAL STYLE",
            "GENDER WOMANS",
            "RS 8.75"
        ],
        "price": 119.99,
        "distance": 323.8009,
        "storeNumber": "03067",
        "shortName": "C3067"
    },
    {
        "itemName": "Wed Band",
        "longICN": "030854028490100500",
        "details": [
            "Y/G",
            "14 KT.",
            "APPRX 1.9 GRM",
            "RS 8",
            "6",
            "RND SHP",
            "DIA-TEST POS STN",
            "@ 1 PTS EA."
        ],
        "price": 109.99,
        "distance": 323.8009,
        "storeNumber": "03067",
        "shortName": "C3067"
    },
    {
        "itemName": "Wed Band",
        "longICN": "031041004667100600",
        "details": [
            "W/G",
            "14 KT.",
            "APPRX 5.4 GRM",
            "TRADITIONAL STYLE",
            "RS 5"
        ],
        "price": 239.99,
        "distance": 323.9995,
        "storeNumber": "03104",
        "shortName": "C3104"
    },
    {
        "itemName": "Wed Band",
        "longICN": "031041004667100700",
        "details": [
            "W/G",
            "10 KT.",
            "APPRX 2.7 GRM",
            "TRADITIONAL STYLE",
            "RS 5",
            "2",
            "RND SHP",
            "DIA-TEST POS STN",
            "@ 1 PTS EA."
        ],
        "price": 89.99,
        "distance": 323.9995,
        "storeNumber": "03104",
        "shortName": "C3104"
    },
    {
        "itemName": "Wed Band",
        "longICN": "031041004881100200",
        "details": [
            "W/G",
            "14 KT.",
            "APPRX 4.1 GRM",
            "TRADITIONAL STYLE",
            "GENDER WOMANS",
            "RS 6",
            "5",
            "RND SHP",
            "DIA-TEST POS STN",
            "@ 0.5 PTS EA."
        ],
        "price": 159.99,
        "distance": 323.9995,
        "storeNumber": "03104",
        "shortName": "C3104"
    },
    {
        "itemName": "Wed Band",
        "longICN": "031041005193100500",
        "details": [
            "W/G",
            "14 KT.",
            "APPRX 9.1 GRM",
            "TRADITIONAL STYLE",
            "GENDER MAN'S",
            "RS 11"
        ],
        "price": 359.99,
        "distance": 323.9995,
        "storeNumber": "03104",
        "shortName": "C3104"
    },
    {
        "itemName": "Wed Band",
        "longICN": "031043011298200500",
        "details": [
            "Y/G",
            "10 KT.",
            "APPRX 3.6 GRM",
            "MODERN STYLE",
            "GENDER MAN'S",
            "RS 10",
            "3",
            "RND SHP",
            "DIA-TEST POS STN",
            "@ 0.5 PTS EA."
        ],
        "price": 199.99,
        "distance": 323.9995,
        "storeNumber": "03104",
        "shortName": "C3104"
    },
    {
        "itemName": "Wed Band",
        "longICN": "031043011442200300",
        "details": [
            "Y/G",
            "14 KT.",
            "APPRX 3.5 GRM",
            "RS 5.5",
            "10",
            "square SHP",
            "DIA-TEST POS STN",
            "@ 2 PTS EA."
        ],
        "price": 159.99,
        "distance": 323.9995,
        "storeNumber": "03104",
        "shortName": "C3104"
    },
    {
        "itemName": "Wed Band",
        "longICN": "031043011533200300",
        "details": [
            "Y/G",
            "14 KT.",
            "APPRX 4.2 GRM",
            "RS 10"
        ],
        "price": 159.99,
        "distance": 323.9995,
        "storeNumber": "03104",
        "shortName": "C3104"
    },
    {
        "itemName": "Wed Band",
        "longICN": "031043014829100200",
        "details": [
            "Y/G",
            "14 KT.",
            "APPRX 3.3 GRM",
            "MODERN STYLE",
            "GENDER WOMANS",
            "RS 8",
            "16",
            "BAG SHP",
            "DIA-TEST POS STN",
            "@ 6 PTS EA."
        ],
        "price": 329.99,
        "distance": 323.9995,
        "storeNumber": "03104",
        "shortName": "C3104"
    },
    {
        "itemName": "Misc Wed Band",
        "longICN": "031043015119100100",
        "details": [
            "Y/G",
            "14 KT.",
            "APPRX 5.1 GRM",
            "TRADITIONAL STYLE",
            "RS 11.5"
        ],
        "price": 239.99,
        "distance": 323.9995,
        "storeNumber": "03104",
        "shortName": "C3104"
    },
    {
        "itemName": "Wed Band",
        "longICN": "031043017020100100",
        "details": [
            "Y/G",
            "10 KT.",
            "APPRX 3.4 GRM",
            "MODERN STYLE",
            "GENDER MAN'S",
            "RS 11",
            "10",
            "RND SHP",
            "DIA-TEST POS STN",
            "@ 1 PTS EA."
        ],
        "price": 119.99,
        "distance": 323.9995,
        "storeNumber": "03104",
        "shortName": "C3104"
    },
    {
        "itemName": "Wed Band",
        "longICN": "031043017116100200",
        "details": [
            "Y/G",
            "14 KT.",
            "APPRX 3.8 GRM",
            "MODERN STYLE",
            "GENDER MAN'S",
            "RS 9",
            "3",
            "RND SHP",
            "DIA-TEST POS STN",
            "@ 1 PTS EA."
        ],
        "price": 159.99,
        "distance": 323.9995,
        "storeNumber": "03104",
        "shortName": "C3104"
    },
    {
        "itemName": "Wed Band",
        "longICN": "031043017945100300",
        "details": [
            "Y/G",
            "14 KT.",
            "APPRX 6.4 GRM",
            "TRADITIONAL STYLE",
            "GENDER MAN'S",
            "RS 10"
        ],
        "price": 259.99,
        "distance": 323.9995,
        "storeNumber": "03104",
        "shortName": "C3104"
    },
    {
        "itemName": "Wed Band",
        "longICN": "031043018335100100",
        "details": [
            "Y/G",
            "14 KT.",
            "APPRX 5.3 GRM",
            "RS 9.5",
            "4",
            "RND SHP",
            "DIA-TEST POS STN",
            "@ 2 PTS EA."
        ],
        "price": 219.99,
        "distance": 323.9995,
        "storeNumber": "03104",
        "shortName": "C3104"
    },
    {
        "itemName": "Wed Band",
        "longICN": "031044012537200100",
        "details": [
            "Y/G",
            "14 KT.",
            "APPRX 9.8 GRM",
            "MODERN STYLE",
            "RS 7.5"
        ],
        "price": 399.99,
        "distance": 323.9995,
        "storeNumber": "03104",
        "shortName": "C3104"
    },
    {
        "itemName": "Wed Band",
        "longICN": "031044012540200100",
        "details": [
            "W/G",
            "14 KT.",
            "APPRX 5.7 GRM",
            "RS 6"
        ],
        "price": 229.99,
        "distance": 323.9995,
        "storeNumber": "03104",
        "shortName": "C3104"
    },
    {
        "itemName": "Misc Wed Band",
        "longICN": "031044013029200400",
        "details": [
            "Y/G",
            "10 KT.",
            "APPRX 1.3 GRM",
            "MODERN STYLE",
            "RS 7.75"
        ],
        "price": 39.99,
        "distance": 323.9995,
        "storeNumber": "03104",
        "shortName": "C3104"
    },
    {
        "itemName": "Wed Band",
        "longICN": "031044013070200100",
        "details": [
            "Y/G",
            "14 KT.",
            "APPRX 3.2 GRM",
            "RS 11"
        ],
        "price": 159.99,
        "distance": 323.9995,
        "storeNumber": "03104",
        "shortName": "C3104"
    },
    {
        "itemName": "Wed Band",
        "longICN": "031044013086200300",
        "details": [
            "Y/G",
            "14 KT.",
            "APPRX 4.6 GRM",
            "RS 8"
        ],
        "price": 179.99,
        "distance": 323.9995,
        "storeNumber": "03104",
        "shortName": "C3104"
    },
    {
        "itemName": "Wed Band",
        "longICN": "031044013181200400",
        "details": [
            "Y/G",
            "14 KT.",
            "APPRX 4.4 GRM",
            "MODERN STYLE",
            "RS 9",
            "5",
            "RND SHP",
            "DIA-TEST POS STN",
            "@ 1.5 PTS EA."
        ],
        "price": 179.99,
        "distance": 323.9995,
        "storeNumber": "03104",
        "shortName": "C3104"
    },
    {
        "itemName": "Wed Band",
        "longICN": "031044013299200100",
        "details": [
            "W/G",
            "10 KT.",
            "APPRX 5.4 GRM",
            "RS 18"
        ],
        "price": 179.99,
        "distance": 323.9995,
        "storeNumber": "03104",
        "shortName": "C3104"
    },
    {
        "itemName": "Wed Band",
        "longICN": "031044013392200100",
        "details": [
            "Y/G",
            "14 KT.",
            "APPRX 2.0 GRM",
            "RS 6.75"
        ],
        "price": 89.99,
        "distance": 323.9995,
        "storeNumber": "03104",
        "shortName": "C3104"
    },
    {
        "itemName": "Wed Band",
        "longICN": "031044013392200200",
        "details": [
            "Y/G",
            "14 KT.",
            "APPRX 4.8 GRM",
            "RS 10"
        ],
        "price": 199.99,
        "distance": 323.9995,
        "storeNumber": "03104",
        "shortName": "C3104"
    },
    {
        "itemName": "Wed Band",
        "longICN": "031044013399200100",
        "details": [
            "W/G",
            "14 KT.",
            "APPRX 3.6 GRM",
            "RS 7",
            "9",
            "RND SHP",
            "DIA-TEST POS STN",
            "@ 4 PTS EA."
        ],
        "price": 219.99,
        "distance": 323.9995,
        "storeNumber": "03104",
        "shortName": "C3104"
    },
    {
        "itemName": "Wed Band",
        "longICN": "031044013562200100",
        "details": [
            "W/G",
            "14 KT.",
            "APPRX 4.1 GRM",
            "TRADITIONAL STYLE",
            "GENDER MAN'S",
            "RS 10.5"
        ],
        "price": 169.99,
        "distance": 323.9995,
        "storeNumber": "03104",
        "shortName": "C3104"
    },
    {
        "itemName": "Wed Band",
        "longICN": "031044013598200100",
        "details": [
            "W/G",
            "14 KT.",
            "APPRX 2.7 GRM",
            "MODERN STYLE",
            "RS 9.5",
            "7",
            "RND SHP",
            "DIA-TEST POS STN",
            "@ 6 PTS EA."
        ],
        "price": 219.99,
        "distance": 323.9995,
        "storeNumber": "03104",
        "shortName": "C3104"
    },
    {
        "itemName": "Wed Band",
        "longICN": "031044013631200100",
        "details": [
            "W/G",
            "14 KT.",
            "APPRX 5.4 GRM",
            "RS 7"
        ],
        "price": 229.99,
        "distance": 323.9995,
        "storeNumber": "03104",
        "shortName": "C3104"
    },
    {
        "itemName": "Wed Band",
        "longICN": "031044013631200200",
        "details": [
            "W/G",
            "14 KT.",
            "APPRX 5.4 GRM",
            "RS 8"
        ],
        "price": 229.99,
        "distance": 323.9995,
        "storeNumber": "03104",
        "shortName": "C3104"
    },
    {
        "itemName": "Wed Band",
        "longICN": "031044013772200100",
        "details": [
            "Y/G",
            "14 KT.",
            "APPRX 4.5 GRM",
            "RS 9",
            "10",
            "RND SHP",
            "DIA-TEST POS STN",
            "@ 2 PTS EA."
        ],
        "price": 219.99,
        "distance": 323.9995,
        "storeNumber": "03104",
        "shortName": "C3104"
    },
    {
        "itemName": "Wed Band",
        "longICN": "031044013848200200",
        "details": [
            "Y/G",
            "14 KT.",
            "APPRX 4.8 GRM",
            "TRADITIONAL STYLE",
            "GENDER WOMANS",
            "RS 6.5"
        ],
        "price": 199.99,
        "distance": 323.9995,
        "storeNumber": "03104",
        "shortName": "C3104"
    },
    {
        "itemName": "Wed Band",
        "longICN": "031044013929200100",
        "details": [
            "Y/G",
            "14 KT.",
            "APPRX 3.0 GRM",
            "RS 6.5",
            "12",
            "RND SHP",
            "DIA-TEST POS STN",
            "@ 2 PTS EA."
        ],
        "price": 139.99,
        "distance": 323.9995,
        "storeNumber": "03104",
        "shortName": "C3104"
    },
    {
        "itemName": "Wed Band",
        "longICN": "031044013980200300",
        "details": [
            "Y/G",
            "14 KT.",
            "APPRX 2.1 GRM",
            "RS 6",
            "11",
            "RND SHP",
            "DIA-TEST POS STN",
            "@ 2.5 PTS EA."
        ],
        "price": 119.99,
        "distance": 323.9995,
        "storeNumber": "03104",
        "shortName": "C3104"
    },
    {
        "itemName": "Wed Band",
        "longICN": "031044014033200100",
        "details": [
            "Y/G",
            "14 KT.",
            "APPRX 5.2 GRM",
            "RS 9"
        ],
        "price": 199.99,
        "distance": 323.9995,
        "storeNumber": "03104",
        "shortName": "C3104"
    },
    {
        "itemName": "Wed Band",
        "longICN": "031044014095200100",
        "details": [
            "Y/G",
            "14 KT.",
            "APPRX 4.7 GRM",
            "TRADITIONAL STYLE",
            "GENDER MAN'S",
            "RS 12.5"
        ],
        "price": 199.99,
        "distance": 323.9995,
        "storeNumber": "03104",
        "shortName": "C3104"
    },
    {
        "itemName": "Wed Band",
        "longICN": "031044014194200100",
        "details": [
            "Y/G AND W/G",
            "14 KT.",
            "APPRX 5.9 GRM",
            "GENDER MAN'S",
            "RS 10"
        ],
        "price": 239.99,
        "distance": 323.9995,
        "storeNumber": "03104",
        "shortName": "C3104"
    },
    {
        "itemName": "Wed Band",
        "longICN": "031044014194200200",
        "details": [
            "Y/G",
            "18 KT.",
            "APPRX 6.2 GRM",
            "RS 11"
        ],
        "price": 279.99,
        "distance": 323.9995,
        "storeNumber": "03104",
        "shortName": "C3104"
    },
    {
        "itemName": "Wed Band",
        "longICN": "031044014198200100",
        "details": [
            "Y/G",
            "14 KT.",
            "APPRX 6.3 GRM",
            "TRADITIONAL STYLE",
            "GENDER MAN'S",
            "RS 8"
        ],
        "price": 239.99,
        "distance": 323.9995,
        "storeNumber": "03104",
        "shortName": "C3104"
    },
    {
        "itemName": "Wed Band",
        "longICN": "031044014254200200",
        "details": [
            "Y/G",
            "14 KT.",
            "APPRX 2.9 GRM",
            "RS 7.5",
            "12",
            "RND SHP",
            "DIA-TEST POS STN",
            "@ 1 PTS EA."
        ],
        "price": 129.99,
        "distance": 323.9995,
        "storeNumber": "03104",
        "shortName": "C3104"
    },
    {
        "itemName": "Wed Band",
        "longICN": "031044014337200400",
        "details": [
            "Y/G",
            "10 KT.",
            "APPRX 1.9 GRM",
            "RS 5.5",
            "9",
            "RND SHP",
            "DIA-TEST POS STN",
            "@ 1 PTS EA."
        ],
        "price": 69.99,
        "distance": 323.9995,
        "storeNumber": "03104",
        "shortName": "C3104"
    },
    {
        "itemName": "Wed Band",
        "longICN": "031044014451200100",
        "details": [
            "Y/G",
            "10 KT.",
            "APPRX 2.1 GRM",
            "RS 7.5",
            "12",
            "RND SHP",
            "DIA-TEST POS STN",
            "@ 1 PTS EA."
        ],
        "price": 89.99,
        "distance": 323.9995,
        "storeNumber": "03104",
        "shortName": "C3104"
    },
    {
        "itemName": "Wed Band",
        "longICN": "031044014457200100",
        "details": [
            "W/G",
            "10 KT.",
            "APPRX 3.6 GRM",
            "RS 10",
            "20",
            "BAG SHP",
            "DIA-TEST POS STN",
            "@ 1 PTS EA."
        ],
        "price": 119.99,
        "distance": 323.9995,
        "storeNumber": "03104",
        "shortName": "C3104"
    },
    {
        "itemName": "Wed Band",
        "longICN": "031044014488200200",
        "details": [
            "Y/G",
            "10 KT.",
            "APPRX 2.3 GRM",
            "RS 9",
            "5",
            "RND SHP",
            "DIA-TEST POS STN",
            "@ 0.5 PTS EA."
        ],
        "price": 69.99,
        "distance": 323.9995,
        "storeNumber": "03104",
        "shortName": "C3104"
    },
    {
        "itemName": "Wed Band",
        "longICN": "031044014488200300",
        "details": [
            "Y/G",
            "10 KT.",
            "APPRX 2.4 GRM",
            "RS 10",
            "1",
            "RND SHP",
            "DIA-TEST POS STN",
            "@ 0.5 PTS EA."
        ],
        "price": 69.99,
        "distance": 323.9995,
        "storeNumber": "03104",
        "shortName": "C3104"
    },
    {
        "itemName": "Wed Band",
        "longICN": "031044014513200400",
        "details": [
            "Y/G",
            "14 KT.",
            "APPRX 2.7 GRM",
            "MODERN STYLE",
            "GENDER WOMANS",
            "RS 7",
            "12",
            "RND SHP",
            "DIA-TEST POS STN",
            "@ 2 PTS EA."
        ],
        "price": 139.99,
        "distance": 323.9995,
        "storeNumber": "03104",
        "shortName": "C3104"
    },
    {
        "itemName": "Wed Band",
        "longICN": "031044014585200200",
        "details": [
            "ROSE GOLD",
            "14 KT.",
            "APPRX 1.8 GRM",
            "TRADITIONAL STYLE",
            "GENDER WOMANS",
            "RS 7"
        ],
        "price": 69.99,
        "distance": 323.9995,
        "storeNumber": "03104",
        "shortName": "C3104"
    },
    {
        "itemName": "Wed Band",
        "longICN": "031044014703201200",
        "details": [
            "Y/G",
            "14 KT.",
            "APPRX 3.7 GRM",
            "RS 7.5",
            "12",
            "RND SHP",
            "DIA-TEST POS STN",
            "@ 1 PTS EA."
        ],
        "price": 159.99,
        "distance": 323.9995,
        "storeNumber": "03104",
        "shortName": "C3104"
    },
    {
        "itemName": "Wed Band",
        "longICN": "031044014739200100",
        "details": [
            "Y/G",
            "14 KT.",
            "APPRX 4.6 GRM",
            "RS 11.5",
            "10",
            "RND SHP",
            "DIA-TEST POS STN",
            "@ 3 PTS EA."
        ],
        "price": 219.99,
        "distance": 323.9995,
        "storeNumber": "03104",
        "shortName": "C3104"
    },
    {
        "itemName": "Wed Band",
        "longICN": "031044014741200200",
        "details": [
            "Y/G",
            "14 KT.",
            "APPRX 4.1 GRM",
            "RS 8.5",
            "12",
            "RND SHP",
            "DIA-TEST POS STN",
            "@ 4 PTS EA."
        ],
        "price": 219.99,
        "distance": 323.9995,
        "storeNumber": "03104",
        "shortName": "C3104"
    },
    {
        "itemName": "Wed Band",
        "longICN": "031044019108100200",
        "details": [
            "Y/G",
            "10 KT.",
            "APPRX 5 GRM",
            "MODERN STYLE",
            "GENDER MAN'S",
            "RS 14",
            "3",
            "RND SHP",
            "DIA-TEST POS STN",
            "@ 1 PTS EA."
        ],
        "price": 159.99,
        "distance": 323.9995,
        "storeNumber": "03104",
        "shortName": "C3104"
    },
    {
        "itemName": "Wed Band",
        "longICN": "031044019941100100",
        "details": [
            "Y/G",
            "14 KT.",
            "APPRX 14 GRM",
            "RS 12",
            "6",
            "PRINCESS SHP",
            "DIA-TEST POS STN",
            "@ 12 PTS EA."
        ],
        "price": 849.99,
        "distance": 323.9995,
        "storeNumber": "03104",
        "shortName": "C3104"
    },
    {
        "itemName": "Wed Band",
        "longICN": "031044019967100100",
        "details": [
            "W/G",
            "14 KT.",
            "APPRX 3.4 GRM",
            "RS 11",
            "4",
            "RND SHP",
            "DIA-TEST POS STN",
            "@ 3 PTS EA."
        ],
        "price": 189.99,
        "distance": 323.9995,
        "storeNumber": "03104",
        "shortName": "C3104"
    },
    {
        "itemName": "Wed Band",
        "longICN": "031044020082100100",
        "details": [
            "Y/G",
            "14 KT.",
            "APPRX 2.6 GRM",
            "MODERN STYLE",
            "GENDER WOMANS",
            "RS 6",
            "5",
            "PRINCESS SHP",
            "DIA-TEST POS STN",
            "@ 10 PTS EA.",
            "4",
            "PRINCESS SHP",
            "DIA-TEST POS STN",
            "@ 8 PTS EA."
        ],
        "price": 259.99,
        "distance": 323.9995,
        "storeNumber": "03104",
        "shortName": "C3104"
    },
    {
        "itemName": "Wed Band",
        "longICN": "031044020118100100",
        "details": [
            "W/G",
            "10 KT.",
            "APPRX 2.4 GRM",
            "RS 6.75"
        ],
        "price": 79.99,
        "distance": 323.9995,
        "storeNumber": "03104",
        "shortName": "C3104"
    },
    {
        "itemName": "Wed Band",
        "longICN": "031044020229100100",
        "details": [
            "W/G",
            "10 KT.",
            "APPRX 1.7 GRM",
            "GENDER WOMANS",
            "RS 5.75"
        ],
        "price": 49.99,
        "distance": 323.9995,
        "storeNumber": "03104",
        "shortName": "C3104"
    },
    {
        "itemName": "Wed Band",
        "longICN": "031044020460100400",
        "details": [
            "Y/G",
            "14 KT.",
            "APPRX 2.2 GRM",
            "RS 5"
        ],
        "price": 99.99,
        "distance": 323.9995,
        "storeNumber": "03104",
        "shortName": "C3104"
    },
    {
        "itemName": "Wed Band",
        "longICN": "031044020620100200",
        "details": [
            "Y/G",
            "14 KT.",
            "APPRX 3.2 GRM",
            "MODERN STYLE",
            "RS 7.5",
            "12",
            "RND SHP",
            "DIA-TEST POS STN",
            "@ 3 PTS EA."
        ],
        "price": 189.99,
        "distance": 323.9995,
        "storeNumber": "03104",
        "shortName": "C3104"
    }
]