[
    {
        "itemName": "Color Television 5\" - 36\"",
        "longICN": "030674004642200200",
        "details": [
            "MFGR MAGNAVOX",
            "MOD 15MF605T/17",
            "SILVER",
            "ANALOG ONLY TUNER",
            "15\" SCREEN",
            "WITH REMOTE"
        ],
        "price": 49.99,
        "distance": 318.9739,
        "storeNumber": "03114",
        "shortName": "C3114"
    },
    {
        "itemName": "Tv/Video Combo",
        "longICN": "030934003232100100",
        "details": [
            "MFGR TOSHIBA",
            "MOD 20HLV86",
            "GREY",
            "ANALOG ONLY TUNER",
            "20\" SCREEN",
            "WITH REMOTE",
            "DVD"
        ],
        "price": 69.99,
        "distance": 318.9739,
        "storeNumber": "03114",
        "shortName": "C3114"
    },
    {
        "itemName": "Color Television 37\" And Up",
        "longICN": "031143004804100100",
        "details": [
            "MFGR JVC",
            "MOD LT-40A320",
            "BLACK",
            "DIGITAL TUNER",
            "40\" SCREEN",
            "NO REMOTE"
        ],
        "price": 179.99,
        "distance": 318.9739,
        "storeNumber": "03114",
        "shortName": "C3114"
    },
    {
        "itemName": "Color Television 5\" - 36\"",
        "longICN": "031143005578100100",
        "details": [
            "MFGR SYLVANIA",
            "MOD LC195SL9A",
            "DIGITAL TUNER",
            "19\" SCREEN",
            "NO REMOTE"
        ],
        "price": 69.99,
        "distance": 318.9739,
        "storeNumber": "03114",
        "shortName": "C3114"
    },
    {
        "itemName": "Color Television 5\" - 36\"",
        "longICN": "031144002880200300",
        "details": [
            "MFGR VIEWSONIC",
            "MOD VT1900L",
            "19\" SCREEN",
            "NO REMOTE"
        ],
        "price": 49.99,
        "distance": 318.9739,
        "storeNumber": "03114",
        "shortName": "C3114"
    },
    {
        "itemName": "Color Television 5\" - 36\"",
        "longICN": "031144003578200100",
        "details": [
            "MFGR SYLVANIA",
            "MOD LC195SL8",
            "DIGITAL TUNER",
            "19\" SCREEN",
            "WITH REMOTE"
        ],
        "price": 49.99,
        "distance": 318.9739,
        "storeNumber": "03114",
        "shortName": "C3114"
    },
    {
        "itemName": "Color Television 5\" - 36\"",
        "longICN": "031144003631200300",
        "details": [
            "MFGR VIZIO",
            "MOD VO320E",
            "DIGITAL TUNER",
            "32\" SCREEN",
            "NO REMOTE"
        ],
        "price": 109.99,
        "distance": 318.9739,
        "storeNumber": "03114",
        "shortName": "C3114"
    },
    {
        "itemName": "Color Television 5\" - 36\"",
        "longICN": "031144003705200100",
        "details": [
            "MFGR SANSUI",
            "MOD HDLCD1955A",
            "DIGITAL TUNER",
            "19\" SCREEN",
            "NO REMOTE"
        ],
        "price": 59.99,
        "distance": 318.9739,
        "storeNumber": "03114",
        "shortName": "C3114"
    },
    {
        "itemName": "Tv/Video Combo",
        "longICN": "031144003754200100",
        "details": [
            "MFGR DYNEX",
            "MOD DX-LTDVD20",
            "DIGITAL TUNER",
            "20\" SCREEN",
            "WITH REMOTE",
            "DVD"
        ],
        "price": 49.99,
        "distance": 318.9739,
        "storeNumber": "03114",
        "shortName": "C3114"
    },
    {
        "itemName": "Color Television 5\" - 36\"",
        "longICN": "031144003766200100",
        "details": [
            "MFGR SYLVANIA",
            "MOD LC260SS1",
            "DIGITAL TUNER",
            "26\" SCREEN",
            "NO REMOTE"
        ],
        "price": 59.99,
        "distance": 318.9739,
        "storeNumber": "03114",
        "shortName": "C3114"
    },
    {
        "itemName": "Color Television 37\" And Up",
        "longICN": "031144003789200100",
        "details": [
            "MFGR AKAI",
            "MOD PT4250AX/SMS",
            "GREY",
            "DIGITAL TUNER",
            "42\" SCREEN",
            "WITH REMOTE"
        ],
        "price": 89.99,
        "distance": 318.9739,
        "storeNumber": "03114",
        "shortName": "C3114"
    },
    {
        "itemName": "Tv/Video Combo",
        "longICN": "031144003919200100",
        "details": [
            "MFGR EMERSON",
            "MOD LD320EM2",
            "DIGITAL TUNER",
            "32 SCREEN",
            "WITH REMOTE",
            "DVD"
        ],
        "price": 109.99,
        "distance": 318.9739,
        "storeNumber": "03114",
        "shortName": "C3114"
    },
    {
        "itemName": "Color Television 5\" - 36\"",
        "longICN": "031144003927200100",
        "details": [
            "MFGR EMERSON",
            "MOD LC320EM3F",
            "BLACK",
            "DIGITAL TUNER",
            "32\" SCREEN",
            "NO REMOTE"
        ],
        "price": 109.99,
        "distance": 318.9739,
        "storeNumber": "03114",
        "shortName": "C3114"
    },
    {
        "itemName": "Color Television 5\" - 36\"",
        "longICN": "031144003936200100",
        "details": [
            "MFGR SUPERSONIC",
            "MOD SC-191",
            "DIGITAL TUNER",
            "19\" SCREEN",
            "NO REMOTE"
        ],
        "price": 49.99,
        "distance": 318.9739,
        "storeNumber": "03114",
        "shortName": "C3114"
    },
    {
        "itemName": "Color Television 5\" - 36\"",
        "longICN": "031144003942200100",
        "details": [
            "MFGR VIZIO",
            "MOD VW26L",
            "BLACK",
            "DIGITAL TUNER",
            "26\" SCREEN",
            "NO REMOTE"
        ],
        "price": 59.99,
        "distance": 318.9739,
        "storeNumber": "03114",
        "shortName": "C3114"
    },
    {
        "itemName": "Color Television 5\" - 36\"",
        "longICN": "031144006276100100",
        "details": [
            "MFGR DYNEX",
            "MOD DX-32L100A11",
            "DIGITAL TUNER",
            "32\" SCREEN",
            "WITH REMOTE"
        ],
        "price": 109.99,
        "distance": 318.9739,
        "storeNumber": "03114",
        "shortName": "C3114"
    },
    {
        "itemName": "Color Television 37\" And Up",
        "longICN": "031144006398100100",
        "details": [
            "MFGR SANYO",
            "MOD DP37819",
            "DIGITAL TUNER",
            "37\" SCREEN",
            "WITH REMOTE"
        ],
        "price": 199.99,
        "distance": 318.9739,
        "storeNumber": "03114",
        "shortName": "C3114"
    },
    {
        "itemName": "Color Television 5\" - 36\"",
        "longICN": "031144006503100100",
        "details": [
            "MFGR LG",
            "MOD 47LS4500-UD",
            "DIGITAL TUNER",
            "47 SCREEN",
            "WITH REMOTE"
        ],
        "price": 379.99,
        "distance": 318.9739,
        "storeNumber": "03114",
        "shortName": "C3114"
    },
    {
        "itemName": "Color Television 5\" - 36\"",
        "longICN": "031144006617100100",
        "details": [
            "MFGR TRUETECH",
            "MOD PLV1615T",
            "DIGITAL TUNER",
            "16\" SCREEN",
            "NO REMOTE"
        ],
        "price": 49.99,
        "distance": 318.9739,
        "storeNumber": "03114",
        "shortName": "C3114"
    },
    {
        "itemName": "Color Television 5\" - 36\"",
        "longICN": "031144006728100100",
        "details": [
            "MFGR PANASONIC",
            "MOD TC-L22X2",
            "22\" SCREEN",
            "WITH REMOTE"
        ],
        "price": 99.99,
        "distance": 318.9739,
        "storeNumber": "03114",
        "shortName": "C3114"
    },
    {
        "itemName": "Color Television 5\" - 36\"",
        "longICN": "031144006888100100",
        "details": [
            "MFGR MAGNAVOX",
            "MOD 15MF400T/37",
            "ANALOG ONLY TUNER",
            "15\" SCREEN",
            "NO REMOTE"
        ],
        "price": 39.99,
        "distance": 318.9739,
        "storeNumber": "03114",
        "shortName": "C3114"
    },
    {
        "itemName": "Color Television 37\" And Up",
        "longICN": "031144007158100100",
        "details": [
            "MFGR TCL",
            "MOD LE55FHDF3302",
            "BLACK",
            "DIGITAL TUNER",
            "55\" SCREEN",
            "WITH REMOTE"
        ],
        "price": 499.99,
        "distance": 318.9739,
        "storeNumber": "03114",
        "shortName": "C3114"
    },
    {
        "itemName": "Color Television 5\" - 36\"",
        "longICN": "031144007202100100",
        "details": [
            "MFGR SANSUI",
            "MOD SLED2490",
            "DIGITAL TUNER",
            "24 SCREEN",
            "NO REMOTE"
        ],
        "price": 69.99,
        "distance": 318.9739,
        "storeNumber": "03114",
        "shortName": "C3114"
    },
    {
        "itemName": "Color Television 5\" - 36\"",
        "longICN": "031144007339100100",
        "details": [
            "MFGR VIZIO",
            "MOD VO22LHDTV10A",
            "DIGITAL TUNER",
            "22\" SCREEN",
            "WITH REMOTE"
        ],
        "price": 99.99,
        "distance": 318.9739,
        "storeNumber": "03114",
        "shortName": "C3114"
    },
    {
        "itemName": "Color Television 5\" - 36\"",
        "longICN": "031144007391100100",
        "details": [
            "MFGR SANSUI",
            "MOD HDLCD1955B",
            "DIGITAL TUNER",
            "19\" SCREEN",
            "NO REMOTE"
        ],
        "price": 49.99,
        "distance": 318.9739,
        "storeNumber": "03114",
        "shortName": "C3114"
    },
    {
        "itemName": "Color Television 37\" And Up",
        "longICN": "031144007620100100",
        "details": [
            "MFGR VIZIO",
            "MOD E550I-A0",
            "55\" SCREEN",
            "WITH REMOTE"
        ],
        "price": 499.99,
        "distance": 318.9739,
        "storeNumber": "03114",
        "shortName": "C3114"
    },
    {
        "itemName": "Color Television 37\" And Up",
        "longICN": "031144007626100100",
        "details": [
            "MFGR PROSCAN",
            "MOD PLDED4016A",
            "DIGITAL TUNER",
            "40\" SCREEN",
            "NO REMOTE"
        ],
        "price": 229.99,
        "distance": 318.9739,
        "storeNumber": "03114",
        "shortName": "C3114"
    },
    {
        "itemName": "Color Television 37\" And Up",
        "longICN": "031144007681100100",
        "details": [
            "MFGR SANYO",
            "MOD DP39E63",
            "39 SCREEN",
            "WITH REMOTE"
        ],
        "price": 199.99,
        "distance": 318.9739,
        "storeNumber": "03114",
        "shortName": "C3114"
    },
    {
        "itemName": "Color Television 5\" - 36\"",
        "longICN": "031144007693100100",
        "details": [
            "MFGR SANYO",
            "MOD DP19657",
            "DIGITAL TUNER",
            "19\" SCREEN",
            "WITH REMOTE"
        ],
        "price": 49.99,
        "distance": 318.9739,
        "storeNumber": "03114",
        "shortName": "C3114"
    },
    {
        "itemName": "Color Television 37\" And Up",
        "longICN": "031144007868100100",
        "details": [
            "MFGR SANYO",
            "MOD DP42841",
            "BLACK",
            "DIGITAL TUNER",
            "42\" SCREEN",
            "NO REMOTE"
        ],
        "price": 249.99,
        "distance": 318.9739,
        "storeNumber": "03114",
        "shortName": "C3114"
    },
    {
        "itemName": "Color Television 5\" - 36\"",
        "longICN": "031144007915100100",
        "details": [
            "MFGR ELEMENT",
            "MOD ELCFW329",
            "BLACK",
            "DIGITAL TUNER",
            "32\" SCREEN",
            "WITH REMOTE"
        ],
        "price": 129.99,
        "distance": 318.9739,
        "storeNumber": "03114",
        "shortName": "C3114"
    },
    {
        "itemName": "Color Television 37\" And Up",
        "longICN": "031144007994100100",
        "details": [
            "MFGR EMERSON",
            "MOD LC391EM3",
            "BLACK",
            "DIGITAL TUNER",
            "39\" SCREEN",
            "WITH REMOTE"
        ],
        "price": 169.99,
        "distance": 318.9739,
        "storeNumber": "03114",
        "shortName": "C3114"
    },
    {
        "itemName": "Tv/Video Combo",
        "longICN": "031144008002100100",
        "details": [
            "MFGR VENTURER",
            "MOD PLV91186CE15",
            "BLACK",
            "DIGITAL TUNER",
            "19\" SCREEN",
            "WITH REMOTE",
            "DVD"
        ],
        "price": 69.99,
        "distance": 318.9739,
        "storeNumber": "03114",
        "shortName": "C3114"
    },
    {
        "itemName": "Color Television 37\" And Up",
        "longICN": "031144008011100100",
        "details": [
            "MFGR HISENSE",
            "MOD 40K360",
            "BLACK",
            "DIGITAL TUNER",
            "40\" SCREEN",
            "NO REMOTE"
        ],
        "price": 169.99,
        "distance": 318.9739,
        "storeNumber": "03114",
        "shortName": "C3114"
    },
    {
        "itemName": "Color Television 5\" - 36\"",
        "longICN": "031144008032100100",
        "details": [
            "MFGR SAMSUNG",
            "MOD LN26B360C5D",
            "DIGITAL TUNER",
            "26\" SCREEN",
            "WITH REMOTE"
        ],
        "price": 119.99,
        "distance": 318.9739,
        "storeNumber": "03114",
        "shortName": "C3114"
    },
    {
        "itemName": "Color Television 5\" - 36\"",
        "longICN": "031144008041100100",
        "details": [
            "MFGR VIZIO",
            "MOD E24I-B1",
            "24 SCREEN",
            "WITH REMOTE"
        ],
        "price": 89.99,
        "distance": 318.9739,
        "storeNumber": "03114",
        "shortName": "C3114"
    },
    {
        "itemName": "Color Television 5\" - 36\"",
        "longICN": "031144008084100100",
        "details": [
            "MFGR VIZIO",
            "MOD E190VA",
            "DIGITAL TUNER",
            "19\" SCREEN",
            "WITH REMOTE"
        ],
        "price": 69.99,
        "distance": 318.9739,
        "storeNumber": "03114",
        "shortName": "C3114"
    },
    {
        "itemName": "Color Television 37\" And Up",
        "longICN": "031144008093100100",
        "details": [
            "MFGR SHARP",
            "MOD LC-40LE431U",
            "DIGITAL TUNER",
            "40\" SCREEN",
            "NO REMOTE"
        ],
        "price": 349.99,
        "distance": 318.9739,
        "storeNumber": "03114",
        "shortName": "C3114"
    },
    {
        "itemName": "Color Television 5\" - 36\"",
        "longICN": "031144008095100100",
        "details": [
            "MFGR SAMSUNG",
            "MOD LN32C350D1DXZA",
            "DIGITAL TUNER",
            "32\" SCREEN",
            "WITH REMOTE"
        ],
        "price": 129.99,
        "distance": 318.9739,
        "storeNumber": "03114",
        "shortName": "C3114"
    },
    {
        "itemName": "Color Television 37\" And Up",
        "longICN": "031144008115100100",
        "details": [
            "MFGR PANASONIC",
            "MOD TC-P42X5",
            "DIGITAL TUNER",
            "42\" SCREEN",
            "NO REMOTE"
        ],
        "price": 199.99,
        "distance": 318.9739,
        "storeNumber": "03114",
        "shortName": "C3114"
    },
    {
        "itemName": "Color Television 5\" - 36\"",
        "longICN": "030674004419200100",
        "details": [
            "MFGR VIZIO",
            "MOD E240AR",
            "YES",
            "DIGITAL TUNER",
            "24 SCREEN",
            "WITH REMOTE"
        ],
        "price": 139.99,
        "distance": 319.7734,
        "storeNumber": "03088",
        "shortName": "C3088"
    },
    {
        "itemName": "Color Television 5\" - 36\"",
        "longICN": "030674010075100100",
        "details": [
            "MFGR PHILIPS",
            "MOD 32PFL4507/F7",
            "BLACK",
            "DIGITAL TUNER",
            "32\" SCREEN",
            "WITH REMOTE"
        ],
        "price": 199.99,
        "distance": 319.7734,
        "storeNumber": "03088",
        "shortName": "C3088"
    },
    {
        "itemName": "Color Television 5\" - 36\"",
        "longICN": "030674010255100100",
        "details": [
            "MFGR PHILIPS",
            "MOD 19PFL4505D/F7",
            "YES",
            "DIGITAL TUNER",
            "19\" SCREEN",
            "WITH REMOTE"
        ],
        "price": 69.99,
        "distance": 319.7734,
        "storeNumber": "03088",
        "shortName": "C3088"
    },
    {
        "itemName": "Color Television 5\" - 36\"",
        "longICN": "030674010305100100",
        "details": [
            "MFGR SANYO",
            "MOD DP19640",
            "YES",
            "DIGITAL TUNER",
            "19\" SCREEN",
            "WITH REMOTE"
        ],
        "price": 99.99,
        "distance": 319.7734,
        "storeNumber": "03088",
        "shortName": "C3088"
    },
    {
        "itemName": "Color Television 5\" - 36\"",
        "longICN": "030674010318100100",
        "details": [
            "MFGR SEIKI",
            "MOD SE32HY27",
            "YES",
            "DIGITAL TUNER",
            "32\" SCREEN",
            "WITH REMOTE"
        ],
        "price": 139.99,
        "distance": 319.7734,
        "storeNumber": "03088",
        "shortName": "C3088"
    },
    {
        "itemName": "Color Television 5\" - 36\"",
        "longICN": "030674010324100100",
        "details": [
            "MFGR VIZIO",
            "MOD E320-B2",
            "BLACK",
            "DIGITAL TUNER",
            "32\" SCREEN",
            "WITH REMOTE"
        ],
        "price": 149.99,
        "distance": 319.7734,
        "storeNumber": "03088",
        "shortName": "C3088"
    },
    {
        "itemName": "Color Television 5\" - 36\"",
        "longICN": "030674010564100100",
        "details": [
            "MFGR SANSUI",
            "MOD SLED2490",
            "BLACK",
            "DIGITAL TUNER",
            "24\" SCREEN",
            "WITH REMOTE"
        ],
        "price": 89.99,
        "distance": 319.7734,
        "storeNumber": "03088",
        "shortName": "C3088"
    },
    {
        "itemName": "Color Television 5\" - 36\"",
        "longICN": "030674011140100100",
        "details": [
            "MFGR RCA",
            "MOD L26HD31",
            "DIGITAL TUNER",
            "26\" SCREEN",
            "WITH REMOTE"
        ],
        "price": 129.99,
        "distance": 319.7734,
        "storeNumber": "03088",
        "shortName": "C3088"
    },
    {
        "itemName": "Color Television 37\" And Up",
        "longICN": "030674011193100100",
        "details": [
            "MFGR SAMSUNG",
            "MOD PN43F4500",
            "DIGITAL TUNER",
            "43\" SCREEN",
            "WITH REMOTE"
        ],
        "price": 289.99,
        "distance": 319.7734,
        "storeNumber": "03088",
        "shortName": "C3088"
    },
    {
        "itemName": "Color Television 37\" And Up",
        "longICN": "030674011809100100",
        "details": [
            "MFGR VIZIO",
            "MOD E500I-A0",
            "BLACK",
            "DIGITAL TUNER",
            "50\" SCREEN",
            "NO REMOTE"
        ],
        "price": 399.99,
        "distance": 319.7734,
        "storeNumber": "03088",
        "shortName": "C3088"
    },
    {
        "itemName": "Color Television 5\" - 36\"",
        "longICN": "030674012106100100",
        "details": [
            "MFGR PROSCAN",
            "MOD PLED1960AD",
            "DIGITAL TUNER",
            "19\" SCREEN",
            "WITH REMOTE"
        ],
        "price": 69.99,
        "distance": 319.7734,
        "storeNumber": "03088",
        "shortName": "C3088"
    },
    {
        "itemName": "Color Television 5\" - 36\"",
        "longICN": "030674012230100100",
        "details": [
            "MFGR ELEMENT",
            "MOD ELEFW328",
            "BLACK",
            "DIGITAL TUNER",
            "32\" SCREEN",
            "WITH REMOTE"
        ],
        "price": 134.99,
        "distance": 319.7734,
        "storeNumber": "03088",
        "shortName": "C3088"
    },
    {
        "itemName": "Color Television 5\" - 36\"",
        "longICN": "030671001326200100",
        "details": [
            "MFGR RCA",
            "MOD L32HD31YX13",
            "BLACK",
            "DIGITAL TUNER",
            "32\" SCREEN",
            "NO REMOTE"
        ],
        "price": 164.99,
        "distance": 323.8009,
        "storeNumber": "03067",
        "shortName": "C3067"
    },
    {
        "itemName": "Color Television 5\" - 36\"",
        "longICN": "030673003735200100",
        "details": [
            "MFGR SHARP",
            "MOD LC-32SV29U",
            "YES",
            "DIGITAL TUNER",
            "32\" SCREEN",
            "WITH REMOTE"
        ],
        "price": 149.99,
        "distance": 323.8009,
        "storeNumber": "03067",
        "shortName": "C3067"
    },
    {
        "itemName": "Color Television 5\" - 36\"",
        "longICN": "030673005964100100",
        "details": [
            "MFGR EMERSON",
            "MOD LC260EM2",
            "YES",
            "DIGITAL TUNER",
            "26\" SCREEN",
            "NO REMOTE"
        ],
        "price": 129.99,
        "distance": 323.8009,
        "storeNumber": "03067",
        "shortName": "C3067"
    },
    {
        "itemName": "Hand Held/Pocket Television",
        "longICN": "030673006644100200",
        "details": [
            "MFGR IVIEW",
            "MOD 700PTV",
            "7 SCREEN"
        ],
        "price": 49.99,
        "distance": 323.8009,
        "storeNumber": "03067",
        "shortName": "C3067"
    },
    {
        "itemName": "Color Television 5\" - 36\"",
        "longICN": "030673007308100100",
        "details": [
            "MFGR EMERSON",
            "MOD LC320EM1",
            "BLACK",
            "DIGITAL TUNER",
            "32\" SCREEN",
            "WITH REMOTE"
        ],
        "price": 169.99,
        "distance": 323.8009,
        "storeNumber": "03067",
        "shortName": "C3067"
    },
    {
        "itemName": "Color Television 37\" And Up",
        "longICN": "030673007470100100",
        "details": [
            "MFGR SAMSUNG",
            "MOD UN46D6000SF",
            "YES",
            "DIGITAL TUNER",
            "46\" SCREEN",
            "WITH REMOTE"
        ],
        "price": 549.99,
        "distance": 323.8009,
        "storeNumber": "03067",
        "shortName": "C3067"
    },
    {
        "itemName": "Color Television 5\" - 36\"",
        "longICN": "030673007563100100",
        "details": [
            "MFGR SYLVANIA",
            "MOD LC320SL1",
            "YES",
            "DIGITAL TUNER",
            "32\" SCREEN",
            "NO REMOTE"
        ],
        "price": 179.99,
        "distance": 323.8009,
        "storeNumber": "03067",
        "shortName": "C3067"
    },
    {
        "itemName": "Color Television 5\" - 36\"",
        "longICN": "030673008015100100",
        "details": [
            "MFGR VIZIO",
            "MOD E320VL",
            "YES",
            "DIGITAL TUNER",
            "32\" SCREEN",
            "WITH REMOTE"
        ],
        "price": 169.99,
        "distance": 323.8009,
        "storeNumber": "03067",
        "shortName": "C3067"
    },
    {
        "itemName": "Color Television 37\" And Up",
        "longICN": "030673008667100100",
        "details": [
            "MFGR RCA",
            "MOD L40FHD41YX9",
            "YES",
            "DIGITAL TUNER",
            "40\" SCREEN",
            "NO REMOTE"
        ],
        "price": 199.99,
        "distance": 323.8009,
        "storeNumber": "03067",
        "shortName": "C3067"
    },
    {
        "itemName": "Color Television 5\" - 36\"",
        "longICN": "030673008787100100",
        "details": [
            "MFGR SCEPTRE",
            "MOD X20SVNAGA",
            "BLACK",
            "DIGITAL TUNER",
            "20\" SCREEN",
            "NO REMOTE"
        ],
        "price": 44.99,
        "distance": 323.8009,
        "storeNumber": "03067",
        "shortName": "C3067"
    },
    {
        "itemName": "Color Television 5\" - 36\"",
        "longICN": "030673009068100100",
        "details": [
            "MFGR VIZIO",
            "MOD VA26LHDTV10T",
            "YES",
            "DIGITAL TUNER",
            "26\" SCREEN",
            "NO REMOTE"
        ],
        "price": 89.99,
        "distance": 323.8009,
        "storeNumber": "03067",
        "shortName": "C3067"
    },
    {
        "itemName": "Color Television 5\" - 36\"",
        "longICN": "030673009110100100",
        "details": [
            "MFGR LG",
            "MOD 32LD350",
            "BLACK",
            "DIGITAL TUNER",
            "32\" SCREEN",
            "WITH REMOTE"
        ],
        "price": 199.99,
        "distance": 323.8009,
        "storeNumber": "03067",
        "shortName": "C3067"
    },
    {
        "itemName": "Color Television 37\" And Up",
        "longICN": "030673009248100100",
        "details": [
            "MFGR JVC",
            "MOD LT-50A330",
            "BLACK",
            "DIGITAL TUNER",
            "50\" SCREEN",
            "WITH REMOTE"
        ],
        "price": 349.99,
        "distance": 323.8009,
        "storeNumber": "03067",
        "shortName": "C3067"
    },
    {
        "itemName": "Color Television 37\" And Up",
        "longICN": "030674004103200100",
        "details": [
            "MFGR RCA",
            "MOD 39LB45RQ",
            "39 SCREEN",
            "WITH REMOTE"
        ],
        "price": 359.99,
        "distance": 323.8009,
        "storeNumber": "03067",
        "shortName": "C3067"
    },
    {
        "itemName": "Color Television 5\" - 36\"",
        "longICN": "030674004327200100",
        "details": [
            "MFGR VIZIO",
            "MOD E320-A0",
            "YES",
            "DIGITAL TUNER",
            "32\" SCREEN",
            "NO REMOTE"
        ],
        "price": 169.99,
        "distance": 323.8009,
        "storeNumber": "03067",
        "shortName": "C3067"
    },
    {
        "itemName": "Color Television 5\" - 36\"",
        "longICN": "030674004331200100",
        "details": [
            "MFGR COBY",
            "MOD TFTV3229",
            "YES",
            "DIGITAL TUNER",
            "32\" SCREEN",
            "NO REMOTE"
        ],
        "price": 199.99,
        "distance": 323.8009,
        "storeNumber": "03067",
        "shortName": "C3067"
    },
    {
        "itemName": "Color Television 5\" - 36\"",
        "longICN": "030674004682200100",
        "details": [
            "MFGR VIORE",
            "MOD LCD2000VT",
            "ANALOG ONLY TUNER",
            "20\" SCREEN",
            "NO REMOTE"
        ],
        "price": 79.99,
        "distance": 323.8009,
        "storeNumber": "03067",
        "shortName": "C3067"
    },
    {
        "itemName": "Color Television 5\" - 36\"",
        "longICN": "030674004718200100",
        "details": [
            "MFGR INSIGNIA",
            "MOD NS-19E720A12",
            "DIGITAL TUNER",
            "19\" SCREEN",
            "WITH REMOTE"
        ],
        "price": 89.99,
        "distance": 323.8009,
        "storeNumber": "03067",
        "shortName": "C3067"
    },
    {
        "itemName": "Color Television 5\" - 36\"",
        "longICN": "030674004758200100",
        "details": [
            "MFGR INSIGNIA",
            "MOD NS-19E320A13",
            "YES",
            "DIGITAL TUNER",
            "19\" SCREEN",
            "WITH REMOTE"
        ],
        "price": 79.99,
        "distance": 323.8009,
        "storeNumber": "03067",
        "shortName": "C3067"
    },
    {
        "itemName": "Color Television 5\" - 36\"",
        "longICN": "030674004812200100",
        "details": [
            "MFGR FUNAI",
            "MOD LC220SL1",
            "YES",
            "DIGITAL TUNER",
            "22\" SCREEN",
            "NO REMOTE"
        ],
        "price": 42.99,
        "distance": 323.8009,
        "storeNumber": "03067",
        "shortName": "C3067"
    },
    {
        "itemName": "Color Television 5\" - 36\"",
        "longICN": "030674004838200200",
        "details": [
            "MFGR ELEMENT",
            "MOD ELCFW329",
            "BLACK",
            "DIGITAL TUNER",
            "32\" SCREEN",
            "WITH REMOTE"
        ],
        "price": 159.99,
        "distance": 323.8009,
        "storeNumber": "03067",
        "shortName": "C3067"
    },
    {
        "itemName": "Color Television 5\" - 36\"",
        "longICN": "030674004840200100",
        "details": [
            "MFGR ELEMENT",
            "MOD ELCFW329",
            "YES",
            "DIGITAL TUNER",
            "32\" SCREEN",
            "WITH REMOTE"
        ],
        "price": 159.99,
        "distance": 323.8009,
        "storeNumber": "03067",
        "shortName": "C3067"
    },
    {
        "itemName": "Color Television 5\" - 36\"",
        "longICN": "030674004863200100",
        "details": [
            "MFGR EMERSON",
            "MOD LF320EM4F",
            "DIGITAL TUNER",
            "32\" SCREEN",
            "WITH REMOTE"
        ],
        "price": 159.99,
        "distance": 323.8009,
        "storeNumber": "03067",
        "shortName": "C3067"
    },
    {
        "itemName": "Color Television 5\" - 36\"",
        "longICN": "030674004902200100",
        "details": [
            "MFGR SONY",
            "MOD KDL32BX330",
            "YES",
            "DIGITAL TUNER",
            "32\" SCREEN",
            "NO REMOTE"
        ],
        "price": 159.99,
        "distance": 323.8009,
        "storeNumber": "03067",
        "shortName": "C3067"
    },
    {
        "itemName": "Color Television 37\" And Up",
        "longICN": "030674004905200200",
        "details": [
            "MFGR SANYO",
            "MOD DP42841",
            "BLACK",
            "DIGITAL TUNER",
            "42\" SCREEN",
            "WITH REMOTE"
        ],
        "price": 209.99,
        "distance": 323.8009,
        "storeNumber": "03067",
        "shortName": "C3067"
    },
    {
        "itemName": "Color Television 5\" - 36\"",
        "longICN": "030674004944200100",
        "details": [
            "MFGR SAMSUNG",
            "MOD UN32H5500AF",
            "BLACK",
            "DIGITAL TUNER",
            "32\" SCREEN",
            "WITH REMOTE"
        ],
        "price": 139.99,
        "distance": 323.8009,
        "storeNumber": "03067",
        "shortName": "C3067"
    },
    {
        "itemName": "Color Television 5\" - 36\"",
        "longICN": "030674004985200100",
        "details": [
            "MFGR DYNEX",
            "MOD DX-L22-10A",
            "DIGITAL TUNER",
            "22\" SCREEN",
            "WITH REMOTE"
        ],
        "price": 89.99,
        "distance": 323.8009,
        "storeNumber": "03067",
        "shortName": "C3067"
    },
    {
        "itemName": "Color Television 37\" And Up",
        "longICN": "030674005060200100",
        "details": [
            "MFGR SAMSUNG",
            "MOD UN40EH5000FXZA",
            "40\" SCREEN",
            "WITH REMOTE"
        ],
        "price": 269.99,
        "distance": 323.8009,
        "storeNumber": "03067",
        "shortName": "C3067"
    },
    {
        "itemName": "Color Television 5\" - 36\"",
        "longICN": "030674005106200100",
        "details": [
            "MFGR EMERSON",
            "MOD LC320EM2",
            "DIGITAL TUNER",
            "32\" SCREEN",
            "NO REMOTE"
        ],
        "price": 89.99,
        "distance": 323.8009,
        "storeNumber": "03067",
        "shortName": "C3067"
    },
    {
        "itemName": "Color Television 5\" - 36\"",
        "longICN": "030674005114200100",
        "details": [
            "MFGR EMERSON",
            "MOD LC320EM2A",
            "DIGITAL TUNER",
            "32\" SCREEN",
            "WITH REMOTE"
        ],
        "price": 129.99,
        "distance": 323.8009,
        "storeNumber": "03067",
        "shortName": "C3067"
    },
    {
        "itemName": "Tv/Video Combo",
        "longICN": "030674005114200200",
        "details": [
            "MFGR POLAROID",
            "MOD 1913-TDXB",
            "DIGITAL TUNER",
            "19\" SCREEN",
            "WITH REMOTE",
            "DVD"
        ],
        "price": 54.99,
        "distance": 323.8009,
        "storeNumber": "03067",
        "shortName": "C3067"
    },
    {
        "itemName": "Color Television 5\" - 36\"",
        "longICN": "030674005173200100",
        "details": [
            "MFGR SANSUI",
            "MOD HDLCD1955A",
            "DIGITAL TUNER",
            "19\" SCREEN",
            "NO REMOTE"
        ],
        "price": 59.99,
        "distance": 323.8009,
        "storeNumber": "03067",
        "shortName": "C3067"
    },
    {
        "itemName": "Color Television 37\" And Up",
        "longICN": "030674005184200100",
        "details": [
            "MFGR SONY",
            "MOD KDL-40R350B",
            "40\" SCREEN",
            "WITH REMOTE"
        ],
        "price": 219.99,
        "distance": 323.8009,
        "storeNumber": "03067",
        "shortName": "C3067"
    },
    {
        "itemName": "Color Television 37\" And Up",
        "longICN": "030674005256200100",
        "details": [
            "MFGR VIZIO",
            "MOD E421VO",
            "DIGITAL TUNER",
            "42\" SCREEN",
            "NO REMOTE"
        ],
        "price": 169.99,
        "distance": 323.8009,
        "storeNumber": "03067",
        "shortName": "C3067"
    },
    {
        "itemName": "Color Television 5\" - 36\"",
        "longICN": "030674005280200100",
        "details": [
            "MFGR VIZIO",
            "MOD VA26LHDTV10T",
            "DIGITAL TUNER",
            "26\" SCREEN",
            "NO REMOTE"
        ],
        "price": 79.99,
        "distance": 323.8009,
        "storeNumber": "03067",
        "shortName": "C3067"
    },
    {
        "itemName": "Color Television 5\" - 36\"",
        "longICN": "030674005336200100",
        "details": [
            "MFGR SAMSUNG",
            "MOD UN32EH4003V",
            "DIGITAL TUNER",
            "32\" SCREEN",
            "WITH REMOTE"
        ],
        "price": 119.99,
        "distance": 323.8009,
        "storeNumber": "03067",
        "shortName": "C3067"
    },
    {
        "itemName": "Color Television 5\" - 36\"",
        "longICN": "030674005343200100",
        "details": [
            "MFGR EMERSON",
            "MOD LF320EM4",
            "YES",
            "DIGITAL TUNER",
            "32\" SCREEN",
            "WITH REMOTE"
        ],
        "price": 149.99,
        "distance": 323.8009,
        "storeNumber": "03067",
        "shortName": "C3067"
    },
    {
        "itemName": "Color Television 37\" And Up",
        "longICN": "030674005344200100",
        "details": [
            "MFGR VIZIO",
            "MOD E480B2",
            "48\" SCREEN",
            "WITH REMOTE"
        ],
        "price": 199.99,
        "distance": 323.8009,
        "storeNumber": "03067",
        "shortName": "C3067"
    },
    {
        "itemName": "Color Television 5\" - 36\"",
        "longICN": "030674005357200100",
        "details": [
            "MFGR APEX",
            "MOD LE1913M3",
            "19\" SCREEN",
            "WITH REMOTE"
        ],
        "price": 49.99,
        "distance": 323.8009,
        "storeNumber": "03067",
        "shortName": "C3067"
    },
    {
        "itemName": "Color Television 5\" - 36\"",
        "longICN": "030674009449100100",
        "details": [
            "MFGR ELEMENT",
            "MOD ELCFW329",
            "DIGITAL TUNER",
            "32\" SCREEN",
            "WITH REMOTE"
        ],
        "price": 169.99,
        "distance": 323.8009,
        "storeNumber": "03067",
        "shortName": "C3067"
    },
    {
        "itemName": "Color Television 5\" - 36\"",
        "longICN": "030674009485100100",
        "details": [
            "MFGR MAGNAVOX",
            "MOD 32ME303V/F7",
            "BLACK",
            "DIGITAL TUNER",
            "32\" SCREEN",
            "WITH REMOTE"
        ],
        "price": 199.99,
        "distance": 323.8009,
        "storeNumber": "03067",
        "shortName": "C3067"
    },
    {
        "itemName": "Color Television 5\" - 36\"",
        "longICN": "030674009623100100",
        "details": [
            "MFGR SHARP",
            "MOD LC-19SB25U",
            "BLACK",
            "DIGITAL TUNER",
            "19\" SCREEN",
            "WITH REMOTE"
        ],
        "price": 64.99,
        "distance": 323.8009,
        "storeNumber": "03067",
        "shortName": "C3067"
    },
    {
        "itemName": "Color Television 5\" - 36\"",
        "longICN": "030674009713100100",
        "details": [
            "MFGR SANYO",
            "MOD DP19648",
            "BLACK",
            "DIGITAL TUNER",
            "19\" SCREEN",
            "WITH REMOTE"
        ],
        "price": 99.99,
        "distance": 323.8009,
        "storeNumber": "03067",
        "shortName": "C3067"
    },
    {
        "itemName": "Color Television 5\" - 36\"",
        "longICN": "030674009886100200",
        "details": [
            "MFGR FUNAI",
            "MOD 32MD359B\\F7",
            "32\" SCREEN",
            "WITH REMOTE"
        ],
        "price": 159.99,
        "distance": 323.8009,
        "storeNumber": "03067",
        "shortName": "C3067"
    },
    {
        "itemName": "Color Television 5\" - 36\"",
        "longICN": "030674010067100100",
        "details": [
            "MFGR INSIGNIA",
            "MOD NS-24L120A13",
            "BLACK",
            "DIGITAL TUNER",
            "24 SCREEN",
            "WITH REMOTE"
        ],
        "price": 119.99,
        "distance": 323.8009,
        "storeNumber": "03067",
        "shortName": "C3067"
    },
    {
        "itemName": "Color Television 5\" - 36\"",
        "longICN": "030674010134100100",
        "details": [
            "MFGR VIZIO",
            "MOD E320-B0",
            "YES",
            "DIGITAL TUNER",
            "32\" SCREEN",
            "WITH REMOTE"
        ],
        "price": 159.99,
        "distance": 323.8009,
        "storeNumber": "03067",
        "shortName": "C3067"
    },
    {
        "itemName": "Color Television 5\" - 36\"",
        "longICN": "030674010161100100",
        "details": [
            "MFGR LG ELECTRONICS",
            "MOD 32CS460",
            "BLACK",
            "DIGITAL TUNER",
            "32\" SCREEN",
            "WITH REMOTE"
        ],
        "price": 149.99,
        "distance": 323.8009,
        "storeNumber": "03067",
        "shortName": "C3067"
    },
    {
        "itemName": "Color Television 5\" - 36\"",
        "longICN": "030674010167100100",
        "details": [
            "MFGR SAMSUNG",
            "MOD LN32D403",
            "BLACK",
            "DIGITAL TUNER",
            "32\" SCREEN",
            "WITH REMOTE"
        ],
        "price": 219.99,
        "distance": 323.8009,
        "storeNumber": "03067",
        "shortName": "C3067"
    }
]